duckdb_tinyorm_py/__init__.py
duckdb_tinyorm_py/advanced_usage.py
duckdb_tinyorm_py/config.py
duckdb_tinyorm_py/decorators.py
duckdb_tinyorm_py/exceptions.py
duckdb_tinyorm_py/migration.py
duckdb_tinyorm_py/repository.py
duckdb_tinyorm_py/utils.py
duckdb_tinyorm_py-0.1.2.dist-info/LICENSE
duckdb_tinyorm_py-0.1.2.dist-info/METADATA
duckdb_tinyorm_py-0.1.2.dist-info/WHEEL
duckdb_tinyorm_py-0.1.2.dist-info/RECORD
