Metadata-Version: 2.1
Name: duckdb-tinyorm-py
Version: 0.1.2
Summary: A tiny ORM for DuckDB
Home-page: https://github.com/naimsulejmani/duckdb-tinyorm-py
License: MIT
Keywords: duckdb,orm,tinyorm,database
Author: Naim Sulejmani
Author-email: naim.sulejmani@gmail.com
Classifier: License :: OSI Approved :: MIT License
Classifier: Programming Language :: Python :: 2
Classifier: Programming Language :: Python :: 2.7
Classifier: Programming Language :: Python :: 3
Classifier: Programming Language :: Python :: 3.4
Classifier: Programming Language :: Python :: 3.5
Classifier: Programming Language :: Python :: 3.6
Classifier: Programming Language :: Python :: 3.7
Classifier: Programming Language :: Python :: 3.8
Classifier: Programming Language :: Python :: 3.9
Classifier: Programming Language :: Python :: 3.10
Classifier: Programming Language :: Python :: 3.11
Classifier: Programming Language :: Python :: 3.12
Project-URL: Repository, https://github.com/naimsulejmani/duckdb-tinyorm-py
